Metadata-Version: 2.1
Name: Mensajes-patrikb
Version: 6.0
Summary: Un paquete de mensajes de Python
Home-page: https://github.com/patrikborza
Author: Patrik Borza
Author-email: hola@patrik.dev
Classifier: Environment :: Console
Classifier: Intended Audience :: Developers
Classifier: License :: OSI Approved :: MIT License
Classifier: Operating System :: OS Independent
Classifier: Programming Language :: Python
Classifier: Programming Language :: Python :: 3.9
Classifier: Programming Language :: Python :: 3.10
Classifier: Topic :: Utilities
License-File: LICENSE
Requires-Dist: numpy >=1.26.4
